[{"name":"FortSoundCueTemplateBase","superType":"SoundCueTemplate","properties":[],"propertyCount":0},{"name":"EmoteBase","superType":"FortSoundCueTemplateBase","properties":[],"propertyCount":0},{"name":"EmoteFoley","superType":"EmoteBase","properties":[],"propertyCount":0},{"name":"EmoteMusic","superType":"EmoteBase","properties":[],"propertyCount":0},{"name":"EmoteMusic3P","superType":"EmoteBase","properties":[],"propertyCount":0},{"name":"GliderOpenClose","superType":"FortSoundCueTemplateBase","properties":[],"propertyCount":0},{"name":"GliderOpen","superType":"GliderOpenClose","properties":[],"propertyCount":0},{"name":"GliderClose","superType":"GliderOpenClose","properties":[],"propertyCount":0},{"name":"GliderThrustLoop","superType":"FortSoundCueTemplateBase","properties":[],"propertyCount":0},{"name":"GliderThrustStart","superType":"FortSoundCueTemplateBase","properties":[],"propertyCount":0},{"name":"PickaxeImpactEnemy","superType":"FortSoundCueTemplateBase","properties":[],"propertyCount":0},{"name":"PickaxeReady","superType":"FortSoundCueTemplateBase","properties":[],"propertyCount":0},{"name":"PickaxeSwing","superType":"FortSoundCueTemplateBase","properties":[],"propertyCount":0}]