[{"name":"ERuntimeGenerationType","type":"uint8_t","values":["Static","DynamicModifiersOnly","Dynamic","LegacyGeneration","ERuntimeGenerationType_MAX"]},{"name":"ENavCostDisplay","type":"uint8_t","values":["TotalCost","HeuristicOnly","RealCostOnly","ENavCostDisplay_MAX"]},{"name":"ENavSystemOverridePolicy","type":"uint8_t","values":["Override","Append","Skip","ENavSystemOverridePolicy_MAX"]},{"name":"ERecastPartitioning","type":"uint8_t","values":["Monotone","Watershed","ChunkyMonotone","ERecastPartitioning_MAX"]}]