[{"name":"WheelSetup","properties":[{"index":0,"name":"WheelClass","mappingType":{"type":"ObjectProperty","objectType":"Class"}},{"index":1,"name":"BoneName","mappingType":{"type":"NameProperty"}},{"index":2,"name":"AdditionalOffset","mappingType":{"type":"StructProperty","structType":"Vector"}},{"index":3,"name":"bDisableSteering","mappingType":{"type":"BoolProperty"}}],"propertyCount":4},{"name":"ReplicatedVehicleState","properties":[{"index":0,"name":"SteeringInput","mappingType":{"type":"FloatProperty"}},{"index":1,"name":"ThrottleInput","mappingType":{"type":"FloatProperty"}},{"index":2,"name":"BrakeInput","mappingType":{"type":"FloatProperty"}},{"index":3,"name":"HandbrakeInput","mappingType":{"type":"FloatProperty"}},{"index":4,"name":"CurrentGear","mappingType":{"type":"IntProperty"}}],"propertyCount":5},{"name":"VehicleInputRate","properties":[{"index":0,"name":"RiseRate","mappingType":{"type":"FloatProperty"}},{"index":1,"name":"FallRate","mappingType":{"type":"FloatProperty"}}],"propertyCount":2},{"name":"TireConfigMaterialFriction","properties":[{"index":0,"name":"PhysicalMaterial","mappingType":{"type":"ObjectProperty","objectType":"PhysicalMaterial"}},{"index":1,"name":"FrictionScale","mappingType":{"type":"FloatProperty"}}],"propertyCount":2},{"name":"VehicleEngineData","properties":[{"index":0,"name":"TorqueCurve","mappingType":{"type":"StructProperty","structType":"RuntimeFloatCurve"}},{"index":1,"name":"MaxRPM","mappingType":{"type":"FloatProperty"}},{"index":2,"name":"MOI","mappingType":{"type":"FloatProperty"}},{"index":3,"name":"DampingRateFullThrottle","mappingType":{"type":"FloatProperty"}},{"index":4,"name":"DampingRateZeroThrottleClutchEngaged","mappingType":{"type":"FloatProperty"}},{"index":5,"name":"DampingRateZeroThrottleClutchDisengaged","mappingType":{"type":"FloatProperty"}}],"propertyCount":6},{"name":"VehicleDifferential4WData","properties":[{"index":0,"name":"DifferentialType","mappingType":{"type":"EnumProperty","innerType":{"type":"ByteProperty"},"enumName":"EVehicleDifferential4W"}},{"index":1,"name":"FrontRearSplit","mappingType":{"type":"FloatProperty"}},{"index":2,"name":"FrontLeftRightSplit","mappingType":{"type":"FloatProperty"}},{"index":3,"name":"RearLeftRightSplit","mappingType":{"type":"FloatProperty"}},{"index":4,"name":"CentreBias","mappingType":{"type":"FloatProperty"}},{"index":5,"name":"FrontBias","mappingType":{"type":"FloatProperty"}},{"index":6,"name":"RearBias","mappingType":{"type":"FloatProperty"}}],"propertyCount":7},{"name":"VehicleGearData","properties":[{"index":0,"name":"Ratio","mappingType":{"type":"FloatProperty"}},{"index":1,"name":"DownRatio","mappingType":{"type":"FloatProperty"}},{"index":2,"name":"UpRatio","mappingType":{"type":"FloatProperty"}}],"propertyCount":3},{"name":"VehicleTransmissionData","properties":[{"index":0,"name":"bUseGearAutoBox","mappingType":{"type":"BoolProperty"}},{"index":1,"name":"GearSwitchTime","mappingType":{"type":"FloatProperty"}},{"index":2,"name":"GearAutoBoxLatency","mappingType":{"type":"FloatProperty"}},{"index":3,"name":"FinalRatio","mappingType":{"type":"FloatProperty"}},{"index":4,"name":"ForwardGears","mappingType":{"type":"ArrayProperty","innerType":{"type":"StructProperty","structType":"VehicleGearData"}}},{"index":5,"name":"ReverseGearRatio","mappingType":{"type":"FloatProperty"}},{"index":6,"name":"NeutralGearUpRatio","mappingType":{"type":"FloatProperty"}},{"index":7,"name":"ClutchStrength","mappingType":{"type":"FloatProperty"}}],"propertyCount":8},{"name":"AnimNode_WheelHandler","superType":"AnimNode_SkeletalControlBase","properties":[],"propertyCount":0},{"name":"VehicleAnimInstanceProxy","superType":"AnimInstanceProxy","properties":[],"propertyCount":0}]